LICENSE
gatoryaml/__init__.py
gatoryaml/exceptions.py
gatoryaml/gator_yaml.py
gatoryaml-1.0.1.dist-info/LICENSE
gatoryaml-1.0.1.dist-info/WHEEL
gatoryaml-1.0.1.dist-info/METADATA
gatoryaml-1.0.1.dist-info/RECORD
