Metadata-Version: 2.1
Name: gatoryaml
Version: 1.0.1
Summary: Custom YAML-like generator for GatorGrader config files.
Home-page: https://github.com/ullrichd21/GatorYaml
License: MIT
Keywords: GatorYAML,YAML,Gator,GatorGrader,GatorConfig
Author: Danny Ullrich
Requires-Python: >=3.7,<4.0
Classifier: License :: OSI Approved :: MIT License
Classifier: Programming Language :: Python :: 3
Classifier: Programming Language :: Python :: 3.7
Classifier: Programming Language :: Python :: 3.8
Classifier: Programming Language :: Python :: 3.9
Classifier: Programming Language :: Python :: 3.10
Project-URL: Repository, https://github.com/ullrichd21/GatorYaml
